berry_oximeter/__init__.py
berry_oximeter/exceptions.py
berry_oximeter/models.py
berry_oximeter/oximeter.py
berry_oximeter/parser.py
berry_oximeter/py.typed
berry_oximeter-0.0.3.dist-info/METADATA
berry_oximeter-0.0.3.dist-info/WHEEL
berry_oximeter-0.0.3.dist-info/RECORD
