Metadata-Version: 2.4
Name: berry-oximeter
Version: 0.0.3
Summary: Python library for Berry Pulse Oximeter data collection via Bluetooth LE
Project-URL: Homepage, https://github.com/atick-faisal/berry-oximeter
Project-URL: Documentation, https://github.com/atick-faisal/berry-oximeter
Project-URL: Repository, https://github.com/atick-faisal/berry-oximeter
Project-URL: Bug Tracker, https://github.com/atick-faisal/berry-oximeter/issues
Project-URL: Changelog, https://github.com/atick-faisal/berry-oximeter/blob/main/CHANGELOG.md
Author-email: Atick Faisal <atickfaisal@gmail.com>
Maintainer-email: Atick Faisal <atickfaisal@gmail.com>
License-Expression: MIT
Keywords: berry,ble,bluetooth,health,medical,oximeter,pulse,spo2
Classifier: Development Status :: 3 - Alpha
Classifier: Intended Audience :: Developers
Classifier: Intended Audience :: Healthcare Industry
Classifier: License :: OSI Approved :: MIT License
Classifier: Programming Language :: Python :: 3
Classifier: Programming Language :: Python :: 3.10
Classifier: Programming Language :: Python :: 3.11
Classifier: Programming Language :: Python :: 3.12
Classifier: Programming Language :: Python :: 3.13
Classifier: Topic :: Scientific/Engineering :: Medical Science Apps.
Classifier: Topic :: Software Development :: Libraries :: Python Modules
Requires-Python: >=3.10
Requires-Dist: bleak>=0.22.3
